[
    {
        "display": "<span class='qty'>4</span><span class='name'>red bell peppers</span>",
        "qty": "4",
        "input": "4 red bell peppers",
        "name": "red bell peppers"
    },
    {
        "display": "<span class='qty'>2</span><span class='unit'>heads</span><span class='name'>cauliflower</span><span class='comment'>, trimmed and cut into 2-inch florets</span>",
        "comment": ", trimmed and cut into 2-inch florets",
        "unit": "head",
        "name": "cauliflower",
        "input": "2 heads cauliflower, trimmed and cut into 2-inch florets",
        "qty": "2"
    },
    {
        "display": "<span class='qty'>3/4</span><span class='unit'>cup</span><span class='comment'>extra-virgin</span><span class='name'>olive oil</span><span class='comment'>, divided</span>",
        "comment": "extra-virgin, divided",
        "unit": "cup",
        "name": "olive oil",
        "input": "3/4 cup extra-virgin olive oil, divided",
        "qty": "3/4"
    },
    {
        "display": "<span class='qty'>3</span><span class='unit'>tablespoons</span><span class='comment'>fresh</span><span class='name'>lemon juice</span>",
        "comment": "fresh",
        "unit": "tablespoon",
        "name": "lemon juice",
        "input": "3 tablespoons fresh lemon juice",
        "qty": "3"
    },
    {
        "display": "<span class='qty'>1/4</span><span class='unit'>cup</span><span class='comment'>large</span><span class='name'>capers</span><span class='comment'>( not salted ) , drained and rinsed</span>",
        "comment": "large (not salted), drained and rinsed",
        "unit": "cup",
        "name": "capers",
        "input": "1/4 cup large capers (not salted), drained and rinsed",
        "qty": "1/4"
    }
]