[
    {
        "display": "<span class='qty'>2</span><span class='unit'>cups</span><span class='name'>water</span>",
        "unit": "cup",
        "qty": "2",
        "input": "2 cups water",
        "name": "water"
    },
    {
        "display": "<span class='qty'>1/2</span><span class='unit'>cup</span><span class='comment'>fresh</span><span class='name'>lemon juice</span>",
        "comment": "fresh",
        "unit": "cup",
        "name": "lemon juice",
        "input": "1/2 cup fresh lemon juice",
        "qty": "1/2"
    },
    {
        "display": "<span class='qty'>3</span><span class='unit'>pounds</span><span class='comment'>Fuji</span><span class='name'>apples</span><span class='comment'>or other sweet-crisp</span><span class='name'>apples</span>",
        "comment": "Fuji or other sweet-crisp",
        "unit": "pound",
        "name": "apples apples",
        "input": "3 pounds Fuji apples or other sweet-crisp apples",
        "qty": "3"
    },
    {
        "display": "<span class='qty'>3</span><span class='unit'>pounds</span><span class='name'>Granny Smith apples</span><span class='comment'>or other tart</span><span class='name'>apples</span>",
        "comment": "or other tart",
        "unit": "pound",
        "name": "Granny Smith apples apples",
        "input": "3 pounds Granny Smith apples or other tart apples",
        "qty": "3"
    },
    {
        "display": "<span class='qty'>3</span><span class='unit'>pounds</span><span class='name'>Jonathan</span><span class='comment'>or Rome Beauty</span><span class='name'>apples</span><span class='comment'>or other soft-textured</span><span class='name'>apples</span>",
        "comment": "or Rome Beauty or other soft-textured",
        "unit": "pound",
        "name": "Jonathan apples apples",
        "input": "3 pounds Jonathan or Rome Beauty apples or other soft-textured apples",
        "qty": "3"
    },
    {
        "display": "<span class='qty'>2 1/4</span><span class='unit'>cups</span><span class='name'>sugar</span>",
        "unit": "cup",
        "qty": "2 1/4",
        "input": "2 1/4 cups sugar",
        "name": "sugar"
    },
    {
        "display": "<span class='qty'>1 1/2</span><span class='unit'>teaspoons</span><span class='comment'>coarse kosher</span><span class='name'>salt</span>",
        "comment": "coarse kosher",
        "unit": "teaspoon",
        "name": "salt",
        "input": "1 1/2 teaspoons coarse kosher salt",
        "qty": "1 1/2"
    },
    {
        "display": "<span class='qty'>1/2</span><span class='unit'>teaspoon</span><span class='comment'>ground</span><span class='name'>cinnamon</span>",
        "comment": "ground",
        "unit": "teaspoon",
        "name": "cinnamon",
        "input": "1/2 teaspoon ground cinnamon",
        "qty": "1/2"
    },
    {
        "display": "<span class='qty'>1/2</span><span class='unit'>teaspoon</span><span class='comment'>ground</span><span class='name'>allspice</span>",
        "comment": "ground",
        "unit": "teaspoon",
        "name": "allspice",
        "input": "1/2 teaspoon ground allspice",
        "qty": "1/2"
    }
]