[
    {
        "display": "<span class='qty'>2</span><span class='unit'>ounces</span><span class='name'>snow-pea shoots</span><span class='other'>,</span><span class='comment'>halved ( 2 cups )</span>",
        "comment": "halved (2 cups)",
        "other": ",",
        "unit": "ounce",
        "name": "snow-pea shoots",
        "input": "2 ounces snow-pea shoots, halved (2 cups)",
        "qty": "2"
    },
    {
        "display": "<span class='qty'>3/4</span><span class='unit'>pound</span><span class='comment'>trimmed</span><span class='name'>kohlrabi bulbs</span>",
        "comment": "trimmed",
        "unit": "pound",
        "name": "kohlrabi bulbs",
        "input": "3/4 pound trimmed kohlrabi bulbs",
        "qty": "3/4"
    },
    {
        "display": "<span class='other'>1/3</span><span class='unit'>cup</span><span class='name'>Japanese-style sesame seeds</span><span class='other'>(</span><span class='comment'>not hulled ) ,</span>",
        "comment": "not hulled) ,",
        "other": "1/3 (",
        "unit": "cup",
        "input": "1/3 cup Japanese-style sesame seeds (not hulled) ,",
        "name": "Japanese-style sesame seeds"
    },
    {
        "display": "<span class='other'>3 tablespoons plus 1</span><span class='unit'>teaspoon</span><span class='comment'>reduced-sodium</span><span class='name'>soy sauce</span>",
        "comment": "reduced-sodium",
        "other": "3 tablespoons plus 1",
        "unit": "teaspoon",
        "input": "3 tablespoons plus 1 teaspoon reduced-sodium soy sauce",
        "name": "soy sauce"
    },
    {
        "display": "<span class='qty'>2</span><span class='unit'>teaspoons</span><span class='name'>sugar</span>",
        "unit": "teaspoon",
        "qty": "2",
        "input": "2 teaspoons sugar",
        "name": "sugar"
    },
    {
        "display": "<span class='qty'>2</span><span class='unit'>teaspoons</span><span class='name'>mirin</span><span class='other'>(</span><span class='comment'>Japanese sweet rice wine</span><span class='other'>)</span>",
        "comment": "Japanese sweet rice wine",
        "other": "()",
        "unit": "teaspoon",
        "name": "mirin",
        "input": "2 teaspoons mirin (Japanese sweet rice wine)",
        "qty": "2"
    },
    {
        "display": "<span class='qty'>1</span><span class='unit'>tablespoon</span><span class='name'>water</span>",
        "unit": "tablespoon",
        "qty": "1",
        "input": "1 tablespoon water",
        "name": "water"
    },
    {
        "display": "<span class='qty'>an</span><span class='name'>adjustable-blade slicer</span><span class='comment'>( fitted with julienne blade ) or a julienne peeler;</span><span class='other'>a</span>",
        "comment": "(fitted with julienne blade) or a julienne peeler;",
        "other": "a",
        "name": "adjustable-blade slicer",
        "input": "an adjustable-blade slicer (fitted with julienne blade) or a julienne peeler; a",
        "qty": "an"
    },
    {
        "display": "<span class='other'>(</span><span class='comment'>Japanese sesame-seed-grinding bowl ) or an electric coffee/spice grinder</span>",
        "comment": "Japanese sesame-seed-grinding bowl) or an electric coffee/spice grinder",
        "input": "(Japanese sesame-seed-grinding bowl) or an electric coffee/spice grinder",
        "other": "("
    }
]