[
    {
        "display": "<span class='qty'>1</span><span class='unit'>cup</span><span class='comment'>dried</span><span class='name'>lentils ( preferably small French lentils )</span>",
        "comment": "dried",
        "unit": "cup",
        "name": "lentils (preferably small French lentils)",
        "input": "1 cup dried lentils (preferably small French lentils)",
        "qty": "1"
    },
    {
        "display": "<span class='qty'>1</span><span class='other'>large</span><span class='name'>garlic</span><span class='unit'>clove</span><span class='other'>,</span><span class='comment'>chopped</span>",
        "comment": "chopped",
        "other": "large ,",
        "unit": "clove",
        "name": "garlic",
        "input": "1 large garlic clove, chopped",
        "qty": "1"
    },
    {
        "display": "<span class='qty'>1</span><span class='unit'>teaspoon</span><span class='name'>salt</span><span class='other'>,</span><span class='comment'>or to taste</span>",
        "comment": "or to taste",
        "other": ",",
        "unit": "teaspoon",
        "name": "salt",
        "input": "1 teaspoon salt, or to taste",
        "qty": "1"
    },
    {
        "display": "<span class='qty'>3/4</span><span class='name'>lb tomatoes</span><span class='other'>,</span><span class='comment'>diced ( 2 cups )</span>",
        "comment": "diced (2 cups)",
        "other": ",",
        "name": "lb tomatoes",
        "input": "3/4 lb tomatoes, diced (2 cups)",
        "qty": "3/4"
    },
    {
        "display": "<span class='qty'>4</span><span class='comment'>large</span><span class='name'>scallions</span><span class='comment'>, thinly sliced ( 3/4 cup )</span>",
        "qty": "4",
        "comment": "large, thinly sliced (3/4 cup)",
        "input": "4 large scallions, thinly sliced (3/4 cup)",
        "name": "scallions"
    },
    {
        "display": "<span class='qty'>1/4</span><span class='unit'>cup</span><span class='comment'>chopped fresh</span><span class='name'>dill</span>",
        "comment": "chopped fresh",
        "unit": "cup",
        "name": "dill",
        "input": "1/4 cup chopped fresh dill",
        "qty": "1/4"
    },
    {
        "display": "<span class='qty'>1/4</span><span class='unit'>cup</span><span class='comment'>thinly sliced fresh</span><span class='name'>basil</span>",
        "comment": "thinly sliced fresh",
        "unit": "cup",
        "name": "basil",
        "input": "1/4 cup thinly sliced fresh basil",
        "qty": "1/4"
    },
    {
        "display": "<span class='qty'>3</span><span class='unit'>tablespoons</span><span class='name'>red-wine vinegar</span><span class='other'>,</span><span class='comment'>or to taste</span>",
        "comment": "or to taste",
        "other": ",",
        "unit": "tablespoon",
        "name": "red-wine vinegar",
        "input": "3 tablespoons red-wine vinegar, or to taste",
        "qty": "3"
    },
    {
        "display": "<span class='qty'>1/4</span><span class='unit'>cup</span><span class='comment'>extra-virgin</span><span class='name'>olive oil</span>",
        "comment": "extra-virgin",
        "unit": "cup",
        "name": "olive oil",
        "input": "1/4 cup extra-virgin olive oil",
        "qty": "1/4"
    },
    {
        "display": "<span class='qty'>1/4</span><span class='unit'>teaspoon</span><span class='name'>black pepper</span>",
        "unit": "teaspoon",
        "qty": "1/4",
        "input": "1/4 teaspoon black pepper",
        "name": "black pepper"
    }
]