[
    {
        "display": "<span class='other'>1 1/3</span><span class='unit'>cups</span><span class='comment'>200 g red cherry</span><span class='name'>tomatoes</span><span class='comment'>, cut into 1/4-inch/5-mm dice</span>",
        "comment": "200 g red cherry, cut into 1/4-inch/5-mm dice",
        "other": "1 1/3",
        "unit": "cup",
        "input": "1 1/3 cups 200 g red cherry tomatoes, cut into 1/4-inch/5-mm dice",
        "name": "tomatoes"
    },
    {
        "display": "<span class='other'>1 1/3</span><span class='unit'>cups</span><span class='comment'>200 g yellow cherry</span><span class='name'>tomatoes</span><span class='comment'>, cut into 1/4-inch/5-mm dice</span>",
        "comment": "200 g yellow cherry, cut into 1/4-inch/5-mm dice",
        "other": "1 1/3",
        "unit": "cup",
        "input": "1 1/3 cups 200 g yellow cherry tomatoes, cut into 1/4-inch/5-mm dice",
        "name": "tomatoes"
    },
    {
        "display": "<span class='other'>1 1/3</span><span class='unit'>cups</span><span class='comment'>200 g tiger or plum</span><span class='name'>tomatoes</span><span class='comment'>, cut into 1/4-inch/5-mm dice</span>",
        "comment": "200 g tiger or plum, cut into 1/4-inch/5-mm dice",
        "other": "1 1/3",
        "unit": "cup",
        "input": "1 1/3 cups 200 g tiger or plum tomatoes, cut into 1/4-inch/5-mm dice",
        "name": "tomatoes"
    },
    {
        "display": "<span class='qty'>18</span><span class='unit'>ounce</span><span class='comment'>500 g medium slicing</span><span class='name'>tomatoes</span><span class='comment'>( about 5 ) , cut into 1/4-inch/5-mm dice</span>",
        "comment": "500 g medium slicing (about 5), cut into 1/4-inch/5-mm dice",
        "unit": "ounce",
        "name": "tomatoes",
        "input": "18 ounce 500 g medium slicing tomatoes (about 5), cut into 1/4-inch/5-mm dice",
        "qty": "18"
    },
    {
        "display": "<span class='qty'>1</span><span class='name'>red pepper</span><span class='comment'>, cut into 1/4-inch/5-mm dice ( 1 cup 120 g )</span>",
        "qty": "1",
        "comment": ", cut into 1/4-inch/5-mm dice (1 cup 120 g)",
        "input": "1 red pepper, cut into 1/4-inch/5-mm dice (1 cup 120 g)",
        "name": "red pepper"
    },
    {
        "display": "<span class='qty'>1</span><span class='comment'>small red</span><span class='name'>onion</span><span class='comment'>, finely diced ( rounded 3/4 cup 120 g )</span>",
        "qty": "1",
        "comment": "small red, finely diced (rounded 3/4 cup 120 g)",
        "input": "1 small red onion, finely diced (rounded 3/4 cup 120 g)",
        "name": "onion"
    },
    {
        "display": "<span class='qty'>2</span><span class='unit'>cloves</span><span class='name'>garlic</span><span class='other'>,</span><span class='comment'>crushed</span>",
        "comment": "crushed",
        "other": ",",
        "unit": "clove",
        "name": "garlic",
        "input": "2 cloves garlic, crushed",
        "qty": "2"
    },
    {
        "display": "<span class='qty'>1/2</span><span class='unit'>teaspoon</span><span class='comment'>ground</span><span class='name'>allspice</span>",
        "comment": "ground",
        "unit": "teaspoon",
        "name": "allspice",
        "input": "1/2 teaspoon ground allspice",
        "qty": "1/2"
    },
    {
        "display": "<span class='qty'>2</span><span class='unit'>teaspoons</span><span class='name'>white wine vinegar</span>",
        "unit": "teaspoon",
        "qty": "2",
        "input": "2 teaspoons white wine vinegar",
        "name": "white wine vinegar"
    },
    {
        "display": "<span class='qty'>1 1/2</span><span class='unit'>tablespoons</span><span class='name'>pomegranate molasses</span>",
        "unit": "tablespoon",
        "qty": "1 1/2",
        "input": "1 1/2 tablespoons pomegranate molasses",
        "name": "pomegranate molasses"
    },
    {
        "display": "<span class='qty'>1/4</span><span class='unit'>cup</span><span class='name'>60 ml olive oil</span><span class='comment'>, plus extra to finish</span>",
        "comment": ", plus extra to finish",
        "unit": "cup",
        "name": "60 ml olive oil",
        "input": "1/4 cup 60 ml olive oil, plus extra to finish",
        "qty": "1/4"
    },
    {
        "display": "<span class='qty'>1/2</span><span class='unit'>teaspoon</span><span class='name'>salt</span>",
        "unit": "teaspoon",
        "qty": "1/2",
        "input": "1/2 teaspoon salt",
        "name": "salt"
    },
    {
        "display": "<span class='qty'>1</span><span class='comment'>large</span><span class='name'>pomegranate</span><span class='comment'>, seeds removed ( 1 cup 170 g seeds )</span>",
        "qty": "1",
        "comment": "large, seeds removed (1 cup 170 g seeds)",
        "input": "1 large pomegranate, seeds removed (1 cup 170 g seeds)",
        "name": "pomegranate"
    },
    {
        "display": "<span class='qty'>1</span><span class='unit'>tablespoon</span><span class='comment'>small</span><span class='name'>oregano leaves</span>",
        "comment": "small",
        "unit": "tablespoon",
        "name": "oregano leaves",
        "input": "1 tablespoon small oregano leaves",
        "qty": "1"
    }
]