[
    {
        "display": "<span class='qty'>1</span><span class='other'>(</span><span class='comment'>13.5-ounce ) can</span><span class='name'>coconut milk</span>",
        "comment": "13.5-ounce) can",
        "other": "(",
        "name": "coconut milk",
        "input": "1 (13.5-ounce) can coconut milk",
        "qty": "1"
    },
    {
        "display": "<span class='qty'>1</span><span class='comment'>medium yellow</span><span class='name'>onion</span><span class='comment'>, chopped</span>",
        "qty": "1",
        "comment": "medium yellow, chopped",
        "input": "1 medium yellow onion, chopped",
        "name": "onion"
    },
    {
        "display": "<span class='qty'>3/4</span><span class='unit'>teaspoon</span><span class='comment'>sea</span><span class='name'>salt</span>",
        "comment": "sea",
        "unit": "teaspoon",
        "name": "salt",
        "input": "3/4 teaspoon sea salt",
        "qty": "3/4"
    },
    {
        "display": "<span class='qty'>2</span><span class='unit'>teaspoons</span><span class='comment'>peeled , grated fresh</span><span class='name'>ginger</span>",
        "comment": "peeled, grated fresh",
        "unit": "teaspoon",
        "name": "ginger",
        "input": "2 teaspoons peeled, grated fresh ginger",
        "qty": "2"
    },
    {
        "display": "<span class='qty'>2</span><span class='unit'>teaspoons</span><span class='comment'>Thai yellow or red</span><span class='name'>curry paste</span>",
        "comment": "Thai yellow or red",
        "unit": "teaspoon",
        "name": "curry paste",
        "input": "2 teaspoons Thai yellow or red curry paste",
        "qty": "2"
    },
    {
        "display": "<span class='qty'>1</span><span class='unit'>clove</span><span class='name'>garlic</span><span class='other'>,</span><span class='comment'>peeled and chopped</span>",
        "comment": "peeled and chopped",
        "other": ",",
        "unit": "clove",
        "name": "garlic",
        "input": "1 clove garlic, peeled and chopped",
        "qty": "1"
    },
    {
        "display": "<span class='qty'>12</span><span class='unit'>ounces</span><span class='name'>baby carrots</span><span class='comment'>, quartered lengthwise</span>",
        "comment": ", quartered lengthwise",
        "unit": "ounce",
        "name": "baby carrots",
        "input": "12 ounces baby carrots, quartered lengthwise",
        "qty": "12"
    },
    {
        "display": "<span class='qty'>2 3/4</span><span class='unit'>cups</span><span class='name'>low-sodium vegetable broth</span><span class='other'>,</span><span class='comment'>plus more as needed</span>",
        "comment": "plus more as needed",
        "other": ",",
        "unit": "cup",
        "name": "low-sodium vegetable broth",
        "input": "2 3/4 cups low-sodium vegetable broth, plus more as needed",
        "qty": "2 3/4"
    },
    {
        "display": "<span class='qty'>2</span><span class='unit'>tablespoons</span><span class='comment'>freshly squeezed</span><span class='name'>lime juice</span><span class='comment'>( from about</span><span class='qty'>1</span><span class='comment'>lime )</span>",
        "comment": "freshly squeezed (from about lime)",
        "unit": "tablespoon",
        "name": "lime juice",
        "input": "2 tablespoons freshly squeezed lime juice (from about 1 lime)",
        "qty": "2 1"
    },
    {
        "display": "<span class='qty'>15</span><span class='comment'>large</span><span class='name'>cilantro</span><span class='unit'>sprigs</span><span class='comment'>plus 5 small cilantro sprigs</span>",
        "comment": "large plus 5 small cilantro sprigs",
        "unit": "sprig",
        "name": "cilantro",
        "input": "15 large cilantro sprigs plus 5 small cilantro sprigs",
        "qty": "15"
    },
    {
        "display": "<span class='other'>1/4 cup plus 1</span><span class='unit'>teaspoon</span><span class='comment'>black or white chia seeds</span>",
        "unit": "teaspoon",
        "comment": "black or white chia seeds",
        "input": "1/4 cup plus 1 teaspoon black or white chia seeds",
        "other": "1/4 cup plus 1"
    }
]