[
    {
        "display": "<span class='qty'>2</span><span class='unit'>tablespoons</span><span class='name'>unsalted butter</span>",
        "unit": "tablespoon",
        "qty": "2",
        "input": "2 tablespoons unsalted butter",
        "name": "unsalted butter"
    },
    {
        "display": "<span class='qty'>5</span><span class='unit'>cups</span><span class='comment'>stemmed and finely chopped cremini</span><span class='name'>mushrooms</span><span class='comment'>( about 1 pound )</span>",
        "comment": "stemmed and finely chopped cremini (about 1 pound)",
        "unit": "cup",
        "name": "mushrooms",
        "input": "5 cups stemmed and finely chopped cremini mushrooms (about 1 pound)",
        "qty": "5"
    },
    {
        "display": "<span class='qty'>5</span><span class='name'>garlic</span><span class='unit'>cloves</span><span class='other'>,</span><span class='comment'>chopped</span>",
        "comment": "chopped",
        "other": ",",
        "unit": "clove",
        "name": "garlic",
        "input": "5 garlic cloves, chopped",
        "qty": "5"
    },
    {
        "display": "<span class='name'>Sea salt</span>",
        "input": "Sea salt",
        "name": "Sea salt"
    },
    {
        "display": "<span class='qty'>1/4</span><span class='unit'>cup</span><span class='comment'>ground</span><span class='name'>flaxseed</span><span class='comment'>( flax meal</span><span class='other'>)</span>",
        "comment": "ground (flax meal",
        "other": ")",
        "unit": "cup",
        "name": "flaxseed",
        "input": "1/4 cup ground flaxseed (flax meal)",
        "qty": "1/4"
    },
    {
        "display": "<span class='qty'>1/2</span><span class='unit'>cup</span><span class='comment'>freshly grated</span><span class='name'>Parmesan</span>",
        "comment": "freshly grated",
        "unit": "cup",
        "name": "Parmesan",
        "input": "1/2 cup freshly grated Parmesan",
        "qty": "1/2"
    },
    {
        "display": "<span class='qty'>1</span><span class='unit'>cup</span><span class='comment'>cooked</span><span class='name'>chickpeas</span><span class='comment'>, drained well</span>",
        "comment": "cooked, drained well",
        "unit": "cup",
        "name": "chickpeas",
        "input": "1 cup cooked chickpeas, drained well",
        "qty": "1"
    },
    {
        "display": "<span class='qty'>3</span><span class='name'>Medjool dates</span><span class='other'>,</span><span class='comment'>pitted</span>",
        "comment": "pitted",
        "other": ",",
        "name": "Medjool dates",
        "input": "3 Medjool dates, pitted",
        "qty": "3"
    },
    {
        "display": "<span class='qty'>1/4</span><span class='unit'>cup</span><span class='comment'>fresh flat-leaf</span><span class='name'>parsley leaves</span>",
        "comment": "fresh flat-leaf",
        "unit": "cup",
        "name": "parsley leaves",
        "input": "1/4 cup fresh flat-leaf parsley leaves",
        "qty": "1/4"
    },
    {
        "display": "<span class='qty'>1</span><span class='name'>egg</span>",
        "qty": "1",
        "input": "1 egg",
        "name": "egg"
    },
    {
        "display": "<span class='qty'>1</span><span class='unit'>teaspoon</span><span class='name'>fennel seeds</span>",
        "unit": "teaspoon",
        "qty": "1",
        "input": "1 teaspoon fennel seeds",
        "name": "fennel seeds"
    },
    {
        "display": "<span class='qty'>2 1/2</span><span class='unit'>tablespoons</span><span class='name'>tahini</span>",
        "unit": "tablespoon",
        "qty": "2 1/2",
        "input": "2 1/2 tablespoons tahini",
        "name": "tahini"
    },
    {
        "display": "<span class='qty'>3</span><span class='unit'>tablespoons</span><span class='comment'>tamari or soy</span><span class='name'>sauce</span>",
        "comment": "tamari or soy",
        "unit": "tablespoon",
        "name": "sauce",
        "input": "3 tablespoons tamari or soy sauce",
        "qty": "3"
    },
    {
        "display": "<span class='comment'>Freshly ground</span><span class='name'>pepper</span>",
        "comment": "Freshly ground",
        "input": "Freshly ground pepper",
        "name": "pepper"
    },
    {
        "display": "<span class='qty'>2</span><span class='unit'>cups</span><span class='comment'>cooked and cooled</span><span class='name'>brown rice</span>",
        "comment": "cooked and cooled",
        "unit": "cup",
        "name": "brown rice",
        "input": "2 cups cooked and cooled brown rice",
        "qty": "2"
    },
    {
        "display": "<span class='qty'>1</span><span class='other'>to</span><span class='range_end'>2</span><span class='unit'>tablespoons</span><span class='comment'>rolled</span><span class='name'>oats</span><span class='comment'>, as needed</span>",
        "comment": "rolled, as needed",
        "other": "to",
        "unit": "tablespoon",
        "qty": "1",
        "range_end": "2",
        "input": "1 to 2 tablespoons rolled oats, as needed",
        "name": "oats"
    },
    {
        "display": "<span class='qty'>1</span><span class='unit'>teaspoon</span><span class='comment'>extra-virgin</span><span class='name'>olive oil</span><span class='comment'>or coconut</span><span class='name'>oil</span>",
        "comment": "extra-virgin or coconut",
        "unit": "teaspoon",
        "name": "olive oil oil",
        "input": "1 teaspoon extra-virgin olive oil or coconut oil",
        "qty": "1"
    },
    {
        "display": "<span class='qty'>4</span><span class='comment'>large</span><span class='name'>shallots</span><span class='comment'>, thinly sliced</span>",
        "qty": "4",
        "comment": "large, thinly sliced",
        "input": "4 large shallots, thinly sliced",
        "name": "shallots"
    },
    {
        "display": "<span class='qty'>6</span><span class='comment'>whole grain</span><span class='name'>English muffins</span>",
        "qty": "6",
        "comment": "whole grain",
        "input": "6 whole grain English muffins",
        "name": "English muffins"
    },
    {
        "display": "<span class='qty'>3/4</span><span class='unit'>cup</span><span class='name'>hummus</span>",
        "unit": "cup",
        "qty": "3/4",
        "input": "3/4 cup hummus",
        "name": "hummus"
    },
    {
        "display": "<span class='qty'>2</span><span class='name'>avocados</span><span class='other'>,</span><span class='comment'>peeled and sliced</span>",
        "comment": "peeled and sliced",
        "other": ",",
        "name": "avocados",
        "input": "2 avocados, peeled and sliced",
        "qty": "2"
    },
    {
        "display": "<span class='qty'>2</span><span class='unit'>cups</span><span class='name'>arugula</span>",
        "unit": "cup",
        "qty": "2",
        "input": "2 cups arugula",
        "name": "arugula"
    }
]