[
    {
        "display": "<span class='qty'>1</span><span class='unit'>clove</span><span class='name'>garlic</span>",
        "unit": "clove",
        "qty": "1",
        "input": "1 clove garlic",
        "name": "garlic"
    },
    {
        "display": "<span class='qty'>1</span><span class='unit'>head</span><span class='name'>lettuce</span>",
        "unit": "head",
        "qty": "1",
        "input": "1 head lettuce",
        "name": "lettuce"
    },
    {
        "display": "<span class='name'>Salad greens: curly endive</span><span class='other'>,</span><span class='name'>celery cabbage</span><span class='other'>,</span><span class='comment'>leaves of</span><span class='name'>spinach</span><span class='other'>,</span><span class='comment'>rhubarb chard</span><span class='other'>,</span><span class='comment'>sprigs of</span><span class='name'>watercress</span>",
        "comment": "leaves of rhubarb chard sprigs of",
        "input": "Salad greens: curly endive, celery cabbage, leaves of spinach, rhubarb chard, sprigs of watercress",
        "name": "Salad greens: curly endive celery cabbage spinach watercress",
        "other": ",, , ,"
    },
    {
        "display": "<span class='qty'>1</span><span class='unit'>teaspoon</span><span class='other'>each</span><span class='comment'>fresh cut</span><span class='name'>dill</span><span class='other'>,</span><span class='comment'>basil</span><span class='other'>,</span><span class='comment'>marjoram</span><span class='other'>,</span><span class='comment'>chervil</span>",
        "comment": "fresh cut basil marjoram chervil",
        "other": "each, , ,",
        "unit": "teaspoon",
        "name": "dill",
        "input": "1 teaspoon each fresh cut dill, basil, marjoram, chervil",
        "qty": "1"
    },
    {
        "display": "<span class='qty'>8</span><span class='unit'>tablespoons</span><span class='name'>olive oil</span>",
        "unit": "tablespoon",
        "qty": "8",
        "input": "8 tablespoons olive oil",
        "name": "olive oil"
    },
    {
        "display": "<span class='qty'>2</span><span class='unit'>tablespoons</span><span class='name'>wine vinegar</span>",
        "unit": "tablespoon",
        "qty": "2",
        "input": "2 tablespoons wine vinegar",
        "name": "wine vinegar"
    },
    {
        "display": "<span class='qty'>1</span><span class='unit'>teaspoon</span><span class='name'>salt</span>",
        "unit": "teaspoon",
        "qty": "1",
        "input": "1 teaspoon salt",
        "name": "salt"
    },
    {
        "display": "<span class='qty'>1/2</span><span class='unit'>teaspoon</span><span class='name'>pepper</span>",
        "unit": "teaspoon",
        "qty": "1/2",
        "input": "1/2 teaspoon pepper",
        "name": "pepper"
    },
    {
        "display": "<span class='qty'>1</span><span class='unit'>tablespoon</span><span class='comment'>chopped</span><span class='name'>chives</span>",
        "comment": "chopped",
        "unit": "tablespoon",
        "name": "chives",
        "input": "1 tablespoon chopped chives",
        "qty": "1"
    }
]