[
    {
        "display": "<span class='qty'>2</span><span class='name'>Meyer</span><span class='comment'>or regular</span><span class='name'>lemons</span><span class='comment'>, thinly sliced into rounds , seeds removed</span>",
        "qty": "2",
        "comment": "or regular, thinly sliced into rounds, seeds removed",
        "input": "2 Meyer or regular lemons, thinly sliced into rounds, seeds removed",
        "name": "Meyer lemons"
    },
    {
        "display": "<span class='qty'>8</span><span class='name'>sugar cubes</span>",
        "qty": "8",
        "input": "8 sugar cubes",
        "name": "sugar cubes"
    },
    {
        "display": "<span class='qty'>1 1/2</span><span class='unit'>teaspoons</span><span class='name'>Angostura bitters</span>",
        "unit": "teaspoon",
        "qty": "1 1/2",
        "input": "1 1/2 teaspoons Angostura bitters",
        "name": "Angostura bitters"
    },
    {
        "display": "<span class='qty'>2</span><span class='comment'>( 750-ml ) bottles dry Prosecco or other sparkling wine</span><span class='other'>,</span><span class='comment'>chilled</span>",
        "qty": "2",
        "comment": "(750-ml) bottles dry Prosecco or other sparkling wine chilled",
        "input": "2 (750-ml) bottles dry Prosecco or other sparkling wine, chilled",
        "other": ","
    }
]