[
    {
        "display": "<span class='qty'>1/4</span><span class='unit'>cup</span><span class='name'>olive oil</span>",
        "unit": "cup",
        "qty": "1/4",
        "input": "1/4 cup olive oil",
        "name": "olive oil"
    },
    {
        "display": "<span class='qty'>1/2</span><span class='unit'>cup</span><span class='comment'>finely chopped</span><span class='name'>shallots</span><span class='comment'>( about 2 large )</span>",
        "comment": "finely chopped (about 2 large)",
        "unit": "cup",
        "name": "shallots",
        "input": "1/2 cup finely chopped shallots (about 2 large)",
        "qty": "1/2"
    },
    {
        "display": "<span class='qty'>4</span><span class='name'>garlic</span><span class='unit'>cloves</span><span class='other'>,</span><span class='comment'>minced</span>",
        "comment": "minced",
        "other": ",",
        "unit": "clove",
        "name": "garlic",
        "input": "4 garlic cloves, minced",
        "qty": "4"
    },
    {
        "display": "<span class='qty'>2</span><span class='unit'>tablespoons</span><span class='comment'>drained</span><span class='name'>capers</span><span class='comment'>, chopped</span>",
        "comment": "drained, chopped",
        "unit": "tablespoon",
        "name": "capers",
        "input": "2 tablespoons drained capers, chopped",
        "qty": "2"
    },
    {
        "display": "<span class='name'>Coarse</span><span class='comment'>kosher</span><span class='name'>salt</span>",
        "comment": "kosher",
        "input": "Coarse kosher salt",
        "name": "Coarse salt"
    }
]